rec_avro/__init__.py
rec_avro/core.py
rec_avro-0.0.4.dist-info/LICENSE
rec_avro-0.0.4.dist-info/METADATA
rec_avro-0.0.4.dist-info/WHEEL
rec_avro-0.0.4.dist-info/top_level.txt
rec_avro-0.0.4.dist-info/RECORD
