Metadata-Version: 2.1
Name: rec-avro
Version: 0.0.4
Summary: Avro schema and data converters supporting storing arbitrary nested python data structures.
Home-page: https://github.com/bmizhen/rec-avro
Author: Boris Mizhen
Author-email: rec-avro@boriska.com
License: MIT
Keywords: avro json schema nested
Platform: UNKNOWN
Requires-Python: >=3
